QAD-0.1.1.dist-info/DESCRIPTION.rst
QAD-0.1.1.dist-info/METADATA
QAD-0.1.1.dist-info/RECORD
QAD-0.1.1.dist-info/WHEEL
QAD-0.1.1.dist-info/entry_points.txt
QAD-0.1.1.dist-info/metadata.json
QAD-0.1.1.dist-info/top_level.txt
qad/__init__.py
